{"title":"Conversations: From Mythical to Curative to Poisonous, Mythic Plants w/ Ellen Zachos","link":"https://shows.acast.com/lets-talk-about-myths-baby-greek-roman-mythology-retold/episodes/conversations-mythic-plants-w-ellen-zachos","pubDate":"Fri, 22 Aug 2025 12:48:24 GMT","enclosure":{"url":"https://sphinx.acast.com/p/open/s/67a1934c95d7c2516aeb49a7/e/68a86719718453410e3c9b93/media.mp3","length":"107429388","type":"audio/mpeg"},"content":"<p>Liv and Michaela chat with author and plant and foraging expert Ellen Zachos about all things myth and plant! From mythical plants like moly to which poisonous Hemlock killed Socrates, we're talking all things PLANTS! Find <a href=\"https://www.hachettebookgroup.com/titles/ellen-zachos/mythic-plants/9781523524396/?lens=workman-publishing-company\" rel=\"noopener noreferrer\" target=\"_blank\">Mythic Plants</a> wherever you get your books and learn more from Ellen <a href=\"https://backyardforager.com/\" rel=\"noopener noreferrer\" target=\"_blank\">here</a>. Submit your question for the next Q&amp;A <a href=\"http://mythsbaby.com/questions\" rel=\"noopener noreferrer\" target=\"_blank\">via email</a> or <a href=\"https://www.speakpipe.com/LTAMB\" rel=\"noopener noreferrer\" target=\"_blank\">a voice note</a>. Get ad-free episodes and so, so much more, by subscribing to the Oracle Edition at <a href=\"http://patreon.com/mythsbaby\" rel=\"noopener noreferrer\" target=\"_blank\">patreon.com/mythsbaby</a></p><p>CW/TW: far too many Greek myths involve assault. I try to provide direct warnings when there is reference to anything with overtly traumatic themes but be aware that Greek mythology regularly features assault, death, and many other potentially triggering events.</p><p>Attributions and licensing information for music used in the podcast can be found here:<a href=\"http://mythsbaby.com/sources-attributions\" rel=\"noopener noreferrer\" target=\"_blank\" style=\"background-color: rgb(255, 255, 255);\"> mythsbaby.com/sources-attributions</a>.</p><hr><p style='color:grey; font-size:0.75em;'> Hosted on Acast. See <a style='color:grey;' target='_blank' rel='noopener noreferrer' href='https://acast.com/privacy'>acast.com/privacy</a> for more information.</p>","contentSnippet":"Liv and Michaela chat with author and plant and foraging expert Ellen Zachos about all things myth and plant! From mythical plants like moly to which poisonous Hemlock killed Socrates, we're talking all things PLANTS! Find Mythic Plants wherever you get your books and learn more from Ellen here. Submit your question for the next Q&A via email or a voice note. Get ad-free episodes and so, so much more, by subscribing to the Oracle Edition at patreon.com/mythsbaby\nCW/TW: far too many Greek myths involve assault. I try to provide direct warnings when there is reference to anything with overtly traumatic themes but be aware that Greek mythology regularly features assault, death, and many other potentially triggering events.\nAttributions and licensing information for music used in the podcast can be found here: mythsbaby.com/sources-attributions.\n\n Hosted on Acast. See acast.com/privacy for more information.","guid":"68a86719718453410e3c9b93","isoDate":"2025-08-22T12:48:24.000Z","itunes":{"subtitle":"Plants! plants! plants!","summary":"<p>Liv and Michaela chat with author and plant and foraging expert Ellen Zachos about all things myth and plant! From mythical plants like moly to which poisonous Hemlock killed Socrates, we're talking all things PLANTS! Find <a href=\"https://www.hachettebookgroup.com/titles/ellen-zachos/mythic-plants/9781523524396/?lens=workman-publishing-company\" rel=\"noopener noreferrer\" target=\"_blank\">Mythic Plants</a> wherever you get your books and learn more from Ellen <a href=\"https://backyardforager.com/\" rel=\"noopener noreferrer\" target=\"_blank\">here</a>. Submit your question for the next Q&amp;A <a href=\"http://mythsbaby.com/questions\" rel=\"noopener noreferrer\" target=\"_blank\">via email</a> or <a href=\"https://www.speakpipe.com/LTAMB\" rel=\"noopener noreferrer\" target=\"_blank\">a voice note</a>. Get ad-free episodes and so, so much more, by subscribing to the Oracle Edition at <a href=\"http://patreon.com/mythsbaby\" rel=\"noopener noreferrer\" target=\"_blank\">patreon.com/mythsbaby</a></p><p>CW/TW: far too many Greek myths involve assault. I try to provide direct warnings when there is reference to anything with overtly traumatic themes but be aware that Greek mythology regularly features assault, death, and many other potentially triggering events.</p><p>Attributions and licensing information for music used in the podcast can be found here:<a href=\"http://mythsbaby.com/sources-attributions\" rel=\"noopener noreferrer\" target=\"_blank\" style=\"background-color: rgb(255, 255, 255);\"> mythsbaby.com/sources-attributions</a>.</p><hr><p style='color:grey; font-size:0.75em;'> Hosted on Acast. See <a style='color:grey;' target='_blank' rel='noopener noreferrer' href='https://acast.com/privacy'>acast.com/privacy</a> for more information.</p>","explicit":"false","duration":"2:00:40","image":"https://assets.pippa.io/shows/67a1934c95d7c2516aeb49a7/show-cover.jpg","episode":"725","season":"9","episodeType":"full"}}