{"title":"Why Is Sparta So Weird? Ancient Sparta & The Spartan Mirage (Part One)","link":"https://shows.acast.com/lets-talk-about-myths-baby-a-greek-and-roman-mythology-podcast/episodes/ancient-sparta-the-spartan-mirage-part-one","pubDate":"Tue, 10 Jan 2023 08:00:37 GMT","enclosure":{"url":"https://sphinx.acast.com/p/open/s/67a1934c95d7c2516aeb49a7/e/63b872760d27950011f04c1b/media.mp3","length":"45274367","type":"audio/mpeg"},"content":"<p>In this introduction to the new series on ancient Sparta and the Spartan Mirage, Liv gives a rundown on the history of Archaic and Classical Sparta, truths and misconceptions. <a href=\"http://www.patreon.com/mythsbaby\" rel=\"noopener noreferrer\" target=\"_blank\">Help keep LTAMB going by subscribing to Liv's Patreon for bonus content!</a></p><p>CW/TW: far too many Greek myths involve assault. Given it's fiction, and typically involves gods and/or monsters, I'm not as deferential as I would be were I referencing the real thing.</p><p>Sources: <a href=\"https://www.gutenberg.org/cache/epub/2707/pg2707-images.html#link2H_4_0004\" rel=\"noopener noreferrer\" target=\"_blank\">The History of Herodotus</a>, translated by G. C. Macaulay as found on Project Gutenberg; “Sparta: Reconstructing History from Secrecy, Lies and Myth.” by Anton Powell from A Companion to Sparta; Pausanias' <a href=\"https://www.theoi.com/Text/Pausanias3A.html\" rel=\"noopener noreferrer\" target=\"_blank\">Description of Greece</a> translated by WHS Jones; Plutarch's Life of Lykourgos, translated by Bernadotte Perrin; upcoming conversation episodes also contributed to sourcing. Check out <a href=\"https://www.badancient.com/\" rel=\"noopener noreferrer\" target=\"_blank\">BadAncient.com</a> for misconceptions on the ancient world.</p><p>Attributions and licensing information for music used in the podcast can be found here:<a href=\"http://mythsbaby.com/sources-attributions\" rel=\"noopener noreferrer\" target=\"_blank\"> mythsbaby.com/sources-attributions</a>.</p><hr><p style='color:grey; font-size:0.75em;'> Hosted on Acast. See <a style='color:grey;' target='_blank' rel='noopener noreferrer' href='https://acast.com/privacy'>acast.com/privacy</a> for more information.</p>","contentSnippet":"In this introduction to the new series on ancient Sparta and the Spartan Mirage, Liv gives a rundown on the history of Archaic and Classical Sparta, truths and misconceptions. Help keep LTAMB going by subscribing to Liv's Patreon for bonus content!\nCW/TW: far too many Greek myths involve assault. Given it's fiction, and typically involves gods and/or monsters, I'm not as deferential as I would be were I referencing the real thing.\nSources: The History of Herodotus, translated by G. C. Macaulay as found on Project Gutenberg; “Sparta: Reconstructing History from Secrecy, Lies and Myth.” by Anton Powell from A Companion to Sparta; Pausanias' Description of Greece translated by WHS Jones; Plutarch's Life of Lykourgos, translated by Bernadotte Perrin; upcoming conversation episodes also contributed to sourcing. Check out BadAncient.com for misconceptions on the ancient world.\nAttributions and licensing information for music used in the podcast can be found here: mythsbaby.com/sources-attributions.\n\n Hosted on Acast. See acast.com/privacy for more information.","guid":"63b872760d27950011f04c1b","isoDate":"2023-01-10T08:00:37.000Z","itunes":{"summary":"<p>In this introduction to the new series on ancient Sparta and the Spartan Mirage, Liv gives a rundown on the history of Archaic and Classical Sparta, truths and misconceptions. <a href=\"http://www.patreon.com/mythsbaby\" rel=\"noopener noreferrer\" target=\"_blank\">Help keep LTAMB going by subscribing to Liv's Patreon for bonus content!</a></p><p>CW/TW: far too many Greek myths involve assault. Given it's fiction, and typically involves gods and/or monsters, I'm not as deferential as I would be were I referencing the real thing.</p><p>Sources: <a href=\"https://www.gutenberg.org/cache/epub/2707/pg2707-images.html#link2H_4_0004\" rel=\"noopener noreferrer\" target=\"_blank\">The History of Herodotus</a>, translated by G. C. Macaulay as found on Project Gutenberg; “Sparta: Reconstructing History from Secrecy, Lies and Myth.” by Anton Powell from A Companion to Sparta; Pausanias' <a href=\"https://www.theoi.com/Text/Pausanias3A.html\" rel=\"noopener noreferrer\" target=\"_blank\">Description of Greece</a> translated by WHS Jones; Plutarch's Life of Lykourgos, translated by Bernadotte Perrin; upcoming conversation episodes also contributed to sourcing. Check out <a href=\"https://www.badancient.com/\" rel=\"noopener noreferrer\" target=\"_blank\">BadAncient.com</a> for misconceptions on the ancient world.</p><p>Attributions and licensing information for music used in the podcast can be found here:<a href=\"http://mythsbaby.com/sources-attributions\" rel=\"noopener noreferrer\" target=\"_blank\"> mythsbaby.com/sources-attributions</a>.</p><hr><p style='color:grey; font-size:0.75em;'> Hosted on Acast. See <a style='color:grey;' target='_blank' rel='noopener noreferrer' href='https://acast.com/privacy'>acast.com/privacy</a> for more information.</p>","explicit":"false","duration":"47:03","image":"https://assets.pippa.io/shows/67a1934c95d7c2516aeb49a7/1745960153949-c45f5487-06f3-4e98-a915-4b1158e03e3e.jpeg","episode":"463","season":"6","episodeType":"full"}}